 [
  {
  "kanji": "匕",
  "tipo": "Kanji fuera de las listas oficiales",
  "lecturasOn": [
    "ヒ",
    "HI"
  ],
  "lecturasKun": [
    "さじ",
    "saji"
  ],
  "trazos": 2,
  "radicalClasico": "匕",
  "grado": "1k (dominio)",
  "jlpt": null,
  "frecuencia": 3574,
  "unicode": "5315",
  "imgKanji": "",
  "imgTrazos": "",
  "tituloEs": "",
  "palabras": [
    {
      "jp": "匕",
      "lectura": "かい",
      "romaji": "kai",
      "glosa": "(ok) (n) cuchara"
    },
    {
      "jp": "匕",
      "lectura": "さじ",
      "romaji": "saji",
      "glosa": "(n) cuchara"
    },
    {
      "jp": "匕",
      "lectura": "しゃじ",
      "romaji": "shaji",
      "glosa": "(n) cuchara"
    },
    {
      "jp": "匕首",
      "lectura": "あいくち",
      "romaji": "aikuchi",
      "glosa": "(n) puñal ◆ daga"
    },
    {
      "jp": "匕首",
      "lectura": "ひしゅ",
      "romaji": "hishu",
      "glosa": "(n) puñal ◆ daga"
    },
    {
      "jp": "一匕",
      "lectura": "いっぴ",
      "romaji": "ippi",
      "glosa": "(n) (1) (obsc) una cucharada ◆ (2) una daga"
    }
  ]
}
  ]

